examples/__init__.py
examples/camera.py
examples/debug.py
examples/export.py
examples/forge.py
examples/group.py
examples/light.py
examples/material.py
examples/noise.py
examples/operations.py
examples/params.py
examples/primitives.py
examples/render.py
examples/saving.py
examples/shaping.py
examples/transforms.py
sdforge/__init__.py
sdforge/core.py
sdforge/debug.py
sdforge/export.py
sdforge/loader.py
sdforge/mesh.py
sdforge/render.py
sdforge/utils.py
sdforge/glsl/camera.glsl
sdforge/glsl/debug.glsl
sdforge/glsl/light.glsl
sdforge/glsl/noise.glsl
sdforge/glsl/operations.glsl
sdforge/glsl/primitives.glsl
sdforge/glsl/raymarching.glsl
sdforge/glsl/shaping.glsl
sdforge/glsl/transforms.glsl
sdforge-0.2.0.dist-info/licenses/LICENSE
tests/__init__.py
tests/camera.py
tests/conftest.py
tests/debug.py
tests/export.py
tests/forge.py
tests/group.py
tests/light.py
tests/material.py
tests/noise.py
tests/operations.py
tests/params.py
tests/primitives.py
tests/render.py
tests/saving.py
tests/shaping.py
tests/transforms.py
sdforge-0.2.0.dist-info/METADATA
sdforge-0.2.0.dist-info/WHEEL
sdforge-0.2.0.dist-info/top_level.txt
sdforge-0.2.0.dist-info/RECORD
