Metadata-Version: 2.4
Name: sdforge
Version: 0.2.0
Summary: A Python library for SDF modeling with real-time GLSL rendering and mesh export.
Home-page: https://github.com/nassimberrada/sdforge
Author: nassimberrada
Classifier: Development Status :: 4 - Beta
Classifier: Intended Audience :: Developers
Classifier: Intended Audience :: Science/Research
Classifier: License :: OSI Approved :: MIT License
Classifier: Programming Language :: Python :: 3
Classifier: Topic :: Multimedia :: Graphics :: 3D Modeling
Classifier: Topic :: Scientific/Engineering :: Visualization
Requires-Python: >=3.6
License-File: LICENSE
Requires-Dist: numpy
Requires-Dist: scikit-image>=0.17
Requires-Dist: watchdog
Requires-Dist: moderngl
Requires-Dist: glfw
Provides-Extra: ui
Requires-Dist: imgui[glfw]>=2.0.0; extra == "ui"
Provides-Extra: export
Requires-Dist: pygltflib; extra == "export"
Provides-Extra: full
Requires-Dist: imgui[glfw]>=2.0.0; extra == "full"
Requires-Dist: pygltflib; extra == "full"
Dynamic: author
Dynamic: classifier
Dynamic: description
Dynamic: description-content-type
Dynamic: home-page
Dynamic: license-file
Dynamic: provides-extra
Dynamic: requires-dist
Dynamic: requires-python
Dynamic: summary
